{"cameraMode":{"drawMode":0,"name":"Shaded","section":"Shading Mode"},"sceneLighting":true,"audioPlay":false,"sceneViewState":{"showFog":true,"showMaterialUpdate":false,"showSkybox":true,"showFlares":true,"showImageEffects":true,"showParticleSystems":true},"in2DMode":false,"pivot":{"x":421.2183837890625,"y":-108.84835815429688,"z":438.8319396972656},"rotation":{"x":-0.2229410707950592,"y":-0.32148462533950808,"z":0.0781618058681488,"w":-0.916971743106842},"size":120.95165252685547,"orthographic":false}